paceutils/__init__.py
paceutils-0.0.1.dist-info/LICENSE
paceutils-0.0.1.dist-info/METADATA
paceutils-0.0.1.dist-info/WHEEL
paceutils-0.0.1.dist-info/top_level.txt
paceutils-0.0.1.dist-info/RECORD
