Metadata-Version: 2.1
Name: paceutils
Version: 0.0.1
Summary: Python utility package for PACE Analytics
Home-page: https://upload.pypi.org/legacy/
Author: Alex Xin Tong Wang
Author-email: XinTong.Wang@riotinto.com
License: UNKNOWN
Platform: UNKNOWN
Classifier: Programming Language :: Python :: 3
Classifier: License :: OSI Approved :: MIT License
Classifier: Operating System :: OS Independent
Requires-Python: >=3.6
Requires-Dist: setuptools
Requires-Dist: boto3
Requires-Dist: statsmodels
